nuclyr/config.py
nuclyr/constants.py
nuclyr/exfor.py
nuclyr/mass.py
nuclyr/nndc.py
nuclyr/data/amdc/mass16.dat
nuclyr/data/ripl/abundance.dat
nuclyr/data/ripl/mass-frdm95.dat
nuclyr-0.17.dist-info/LICENSE
nuclyr-0.17.dist-info/METADATA
nuclyr-0.17.dist-info/WHEEL
nuclyr-0.17.dist-info/top_level.txt
nuclyr-0.17.dist-info/RECORD
