Metadata-Version: 2.1
Name: nuclyr
Version: 0.17
Summary: An utility package for nuclear data.
Home-page: https://github.com/phScholz/nuclyr
Author: Philipp Scholz
Author-email: pscholz@outlook.com
License: MIT
Platform: UNKNOWN
Requires-Dist: selenium
Requires-Dist: pandas
Requires-Dist: numpy
Requires-Dist: requests
